quickdraw/__init__.py
quickdraw/data.py
quickdraw/names.py
quickdraw-1.0.0.dist-info/LICENSE
quickdraw-1.0.0.dist-info/METADATA
quickdraw-1.0.0.dist-info/WHEEL
quickdraw-1.0.0.dist-info/top_level.txt
quickdraw-1.0.0.dist-info/RECORD
