Metadata-Version: 2.1
Name: quickdraw
Version: 1.0.0
Summary: An API for downloading and reading the google quickdraw data.
Home-page: https://github.com/martinohanlon/quickdraw_python
Author: Martin O'Hanlon
Author-email: martin@ohanlonweb.com
License: MIT
License-File: LICENSE
